xarray_extras/__init__.py
xarray_extras/csv.py
xarray_extras/cumulatives.py
xarray_extras/interpolate.py
xarray_extras/numba_extras.py
xarray_extras/sort.py
xarray_extras/version.py
xarray_extras/backport/__init__.py
xarray_extras/backport/dask.py
xarray_extras/backport/numpy.py
xarray_extras/duck/__init__.py
xarray_extras/duck/sort.py
xarray_extras/kernels/__init__.py
xarray_extras/kernels/csv.py
xarray_extras/kernels/cumulatives.py
xarray_extras/kernels/interpolate.py
xarray_extras/tests/__init__.py
xarray_extras/tests/test_csv.py
xarray_extras/tests/test_cumulatives.py
xarray_extras/tests/test_interpolate.py
xarray_extras/tests/test_numba_extras.py
xarray_extras/tests/test_sort.py
xarray_extras-0.2.0.dist-info/METADATA
xarray_extras-0.2.0.dist-info/RECORD
xarray_extras-0.2.0.dist-info/WHEEL
xarray_extras-0.2.0.dist-info/top_level.txt
