Metadata-Version: 2.1
Name: xarray-extras
Version: 0.2.0
Summary: Advanced / experimental algorithms for xarray
Home-page: https://github.com/crusaderky/xarray_extras
Author: Guido Imperiale
Author-email: guido.imperiale@gmail.com
License: LGPL
Platform: UNKNOWN
Classifier: Development Status :: 3 - Alpha
Classifier: License :: OSI Approved :: GNU Lesser General Public License v3 or later (LGPLv3+)
Classifier: Operating System :: OS Independent
Classifier: Intended Audience :: Science/Research
Classifier: Programming Language :: Python
Classifier: Programming Language :: Python :: 3
Classifier: Programming Language :: Python :: 3.5
Classifier: Programming Language :: Python :: 3.6
Classifier: Programming Language :: Python :: 3.7
Classifier: Topic :: Scientific/Engineering
Requires-Dist: dask (>=0.17.3)
Requires-Dist: numba (>=0.34)
Requires-Dist: numpy (>=1.13)
Requires-Dist: pandas (>=0.20.2)
Requires-Dist: scipy (>=1.0.0)
Requires-Dist: xarray (>=0.10.0)
